<?xml version="1.0" encoding="UTF-8" ?>
<class name="OpenXRFbHandTrackingMeshExtensionWrapper" inherits="OpenXRExtensionWrapperExtension" xmlns:xsi="http://www.w3.org/2001/XMLSchema-instance" xsi:noNamespaceSchemaLocation="https://raw.githubusercontent.com/godotengine/godot/master/doc/class.xsd">
	<brief_description>
		Wraps the [code]XR_FB_hand_tracking_mesh[/code] extension.
	</brief_description>
	<description>
		Wraps the [code]XR_FB_hand_tracking_mesh[/code] extension.
	</description>
	<tutorials>
	</tutorials>
	<signals>
		<signal name="openxr_fb_hand_tracking_mesh_data_fetched">
			<param index="0" name="hand_index" type="int" />
			<description>
				Emitted when the mesh data has been fetched for the given hand ([code]0[/code] is left, and [code]1[/code] is right).
			</description>
		</signal>
	</signals>
</class>
